datasette_show_errors.py
datasette_show_errors-0.2.dist-info/LICENSE
datasette_show_errors-0.2.dist-info/METADATA
datasette_show_errors-0.2.dist-info/WHEEL
datasette_show_errors-0.2.dist-info/entry_points.txt
datasette_show_errors-0.2.dist-info/top_level.txt
datasette_show_errors-0.2.dist-info/RECORD
