Metadata-Version: 2.1
Name: datasette-show-errors
Version: 0.2
Summary: Datasette plugin for displaying error tracebacks
Home-page: https://github.com/simonw/datasette-show-errors
Author: Simon Willison
License: Apache License, Version 2.0
Platform: UNKNOWN
Requires-Dist: starlette
Requires-Dist: datasette
Provides-Extra: test
Requires-Dist: pytest ; extra == 'test'
